[
  {
    "chunk_id": "1",
    "content": "Công ty: Công ty Cổ phần Khoáng sản và Vật liệu Xây dựng Lâm Đồng và Các Công ty Con\nMã cổ phiếu: Không có thông tin được cung cấp trong báo cáo.\nLoại báo cáo: Báo cáo tài chính hợp nhất đã được soát xét giữa niên độ\nThời gian: Cho kỳ kế toán 06 tháng kết thúc ngày 30 tháng 06 năm 2024 (phát hành ngày 26 tháng 08 năm 2024)\nÝ kiến kiểm toán: Chấp nhận toàn phần (dựa trên báo cáo soát xét)\n\nSection: Thông tin chung và Mục lục\nLoại nội dung: Text\n\nCÔNG TY CỔ PHẦN KHOÁNG SẢN VÀ VẬT LIỆU XÂY DỰNG LÂM ĐỒNG VÀ CÁC CÔNG TY CON\nĐịa chỉ: 87 Phù Đổng Thiên Vương, Phường 8, thành phố Đà Lạt, tỉnh Lâm Đồng, Việt Nam.\n\nMỤC LỤC\nTrang\nBÁO CÁO CỦA BAN TỔNG GIÁM ĐỐC 1 - 2\nBÁO CÁO SOÁT XÉT THÔNG TIN TÀI CHÍNH GIỮA NIÊN ĐỘ 3 - 4\nBÁO CÁO TÀI CHÍNH HỢP NHẤT ĐÃ ĐƯỢC SOÁT XÉT\nBảng cân đối kế toán hợp nhất 5 - 6\nBáo cáo kết quả hoạt động kinh doanh hợp nhất 7\nBáo cáo lưu chuyển tiền tệ hợp nhất 8 - 9\nBản thuyết minh báo cáo tài chính hợp nhất 10 - 51",
    "questions": [
      {
        "question": "Tên đầy đủ của công ty mẹ là gì?",
        "difficulty": "Easy_NER"
      },
      {
        "question": "Địa chỉ trụ sở chính của công ty là gì?",
        "difficulty": "Easy_NER"
      },
      {
        "question": "Báo cáo này là loại báo cáo gì và cho kỳ kế toán nào?",
        "difficulty": "Easy_QA"
      },
      {
        "question": "Trang nào chứa Bảng cân đối kế toán hợp nhất?",
        "difficulty": "Medium_QA"
      },
      {
        "question": "Báo cáo này có bao gồm thuyết minh báo cáo tài chính không? Nếu có, ở các trang nào?",
        "difficulty": "Medium_QA"
      },
      {
        "question": "Ngày phát hành báo cáo tài chính là khi nào?",
        "difficulty": "Easy_NER"
      }
    ]
  },
  {
    "chunk_id": "2",
    "content": "Công ty: Công ty Cổ phần Khoáng sản và Vật liệu Xây dựng Lâm Đồng và Các Công ty Con\nMã cổ phiếu: Không có thông tin được cung cấp trong báo cáo.\nLoại báo cáo: Báo cáo tài chính hợp nhất đã được soát xét giữa niên độ\nThời gian: Cho kỳ kế toán 06 tháng kết thúc ngày 30 tháng 06 năm 2024 (phát hành ngày 26 tháng 08 năm 2024)\nÝ kiến kiểm toán: Chấp nhận toàn phần (dựa trên báo cáo soát xét)\n\nSection: Báo cáo của Ban Tổng Giám đốc (Thành viên Hội đồng Quản trị, Ban Kiểm soát, Ban Tổng Giám đốc)\nLoại nội dung: Text\n\nCÔNG TY CỔ PHẦN KHOÁNG SẢN VÀ VẬT LIỆU XÂY DỰNG LÂM ĐỒNG VÀ CÁC CÔNG TY CON\nĐịa chỉ: 87 Phù Đổng Thiên Vương, Phường 8, thành phố Đà Lạt, tỉnh Lâm Đồng, Việt Nam.\n\nBÁO CÁO CỦA BAN TỔNG GIÁM ĐỐC\nBan Tổng Giám đốc Công ty Cổ phần Khoáng sản và Vật liệu Xây dựng Lâm Đồng (dưới đây gọi tắt là Công ty) đệ trình báo cáo này cùng với các báo cáo tài chính hợp nhất đính kèm đã được soát xét của Công ty và các công ty con (dưới đây cùng với Công ty gọi chung là Tập đoàn) cho kỳ kế toán 06 tháng kết thúc ngày 30 tháng 06 năm 2024.\n\nTHÀNH VIÊN HỘI ĐỒNG QUẢN TRỊ, BAN KIỂM SOÁT VÀ BAN TỔNG GIÁM ĐỐC\nDanh sách các thành viên Hội đồng quản trị trong kỳ và vào ngày lập báo cáo này của Công ty bao gồm:\nÔng Lê Đình Hiển | Chủ tịch\nÔng Nguyễn An Thái | Phó Chủ tịch\nÔng Hầu Văn Tuấn | Thành viên\nÔng Phạm Gia Sâm | Thành viên\nÔng Mai Nam Dương | Thành viên\nÔng Lê Văn Quý | Thành viên\nÔng Ngô Văn Minh | Thành viên\n\nDanh sách các thành viên Bộ phận Kiểm toán nội bộ trực thuộc Hội đồng quản trị trong kỳ và vào ngày lập báo cáo này của Công ty bao gồm:\nBà Nguyễn Thị Ngọc Đức | Trưởng bộ phận\nÔng Trần Quang Thục | Thành viên\nBà Huỳnh Thị Quế Hương | Thành viên\n\nDanh sách các thành viên Ban Kiểm soát trong kỳ và vào ngày lập báo cáo này của Công ty bao gồm:\nÔng Phạm Hồng Hải | Trưởng ban\nBà Nguyễn Thị Thu Hương | Thành viên\nÔng Trần Hùng Phương | Thành viên - Miễn nhiệm ngày 19 tháng 04 năm 2024\nBà Đặng Thị Hằng | Thành viên - Bổ nhiệm ngày 19 tháng 04 năm 2024\n\nDanh sách các thành viên Ban Tài chính Công ty trong kỳ và vào ngày lập báo cáo này bao gồm:\nÔng Hầu Văn Huấn | Giám đốc tài chính\n\nDanh sách các thành viên Ban Tổng Giám đốc của Công ty trong kỳ và vào ngày lập báo cáo này bao gồm:\nÔng Nguyễn An Thái | Tổng Giám đốc\nÔng Trần Văn Hiến | Phó Tổng Giám đốc\nÔng Lê Cao Quang | Phó Tổng Giám đốc\nÔng Nguyễn Quang Duyệt | Phó Tổng Giám đốc\nÔng Nguyễn Thanh Toàn | Phó Tổng Giám đốc\nÔng Lê Thanh Hòa | Phó Tổng Giám đốc\nÔng Lê Nam Đồng | Phó Tổng Giám đốc (miễn nhiệm ngày 01 tháng 05 năm 2024), Kế toán trưởng (bổ nhiệm ngày 01 tháng 05 năm 2024)\nBà Dương Thị Ngọc Ngân | Kế toán trưởng (miễn nhiệm ngày 01 tháng 05 năm 2024)",
    "questions": [
      {
        "question": "Ai là Chủ tịch Hội đồng quản trị của công ty?",
        "difficulty": "Easy_NER"
      },
      {
        "question": "Tổng Giám đốc của công ty là ai?",
        "difficulty": "Easy_NER"
      },
      {
        "question": "Ai được bổ nhiệm làm thành viên Ban Kiểm soát vào ngày 19 tháng 04 năm 2024?",
        "difficulty": "Easy_QA"
      },
      {
        "question": "Kế toán trưởng của công ty tính đến ngày lập báo cáo là ai?",
        "difficulty": "Medium_QA"
      },
      {
        "question": "Có bao nhiêu Phó Tổng Giám đốc được liệt kê trong danh sách?",
        "difficulty": "Medium_QA"
      },
      {
        "question": "Nêu vai trò và tên của Ông Lê Nam Đồng trong kỳ báo cáo.",
        "difficulty": "Medium_QA"
      },
      {
        "question": "Phân tích tầm quan trọng của việc cập nhật danh sách thành viên quản lý cấp cao trong báo cáo tài chính.",
        "difficulty": "Hard_SA"
      }
    ]
  },
  {
    "chunk_id": "3",
    "content": "Công ty: Công ty Cổ phần Khoáng sản và Vật liệu Xây dựng Lâm Đồng và Các Công ty Con\nMã cổ phiếu: Không có thông tin được cung cấp trong báo cáo.\nLoại báo cáo: Báo cáo tài chính hợp nhất đã được soát xét giữa niên độ\nThời gian: Cho kỳ kế toán 06 tháng kết thúc ngày 30 tháng 06 năm 2024 (phát hành ngày 26 tháng 08 năm 2024)\nÝ kiến kiểm toán: Chấp nhận toàn phần (dựa trên báo cáo soát xét)\n\nSection: Báo cáo của Ban Tổng Giám đốc (Kiểm toán viên và Trách nhiệm chung)\nLoại nội dung: Text\n\nBÁO CÁO CỦA BAN TỔNG GIÁM ĐỐC TIẾP THEO\nKIỂM TOÁN VIÊN\nBáo cáo tài chính hợp nhất kèm theo được soát xét bởi Công ty TNHH Kiểm toán - Tư vấn RSM Việt Nam, thành viên RSM Quốc tế.\n\nTRÁCH NHIỆM CỦA BAN TỔNG GIÁM ĐỐC\nBan Tổng Giám đốc Tập đoàn có trách nhiệm lập báo cáo tài chính hợp nhất hàng kỳ phản ánh một cách trung thực và hợp lý tình hình tài chính hợp nhất cũng như kết quả hoạt động kinh doanh hợp nhất và tình hình lưu chuyển tiền tệ hợp nhất của Tập đoàn trong kỳ. Trong việc lập báo cáo tài chính hợp nhất này, Ban Tổng Giám đốc được yêu cầu phải lựa chọn và áp dụng nhất quán các chính sách kế toán thích hợp, đưa ra các xét đoán và ước tính hợp lý, tuân thủ các Chuẩn mực kế toán, lập báo cáo trên cơ sở hoạt động liên tục và duy trì hệ thống kiểm soát nội bộ hữu hiệu để hạn chế sai sót và gian lận.",
    "questions": [
      {
        "question": "Đơn vị kiểm toán soát xét báo cáo tài chính hợp nhất này là ai?",
        "difficulty": "Easy_NER"
      },
      {
        "question": "Theo báo cáo, Ban Tổng Giám đốc có trách nhiệm gì trong việc lập báo cáo tài chính hợp nhất?",
        "difficulty": "Easy_QA"
      },
      {
        "question": "Mục đích của việc duy trì hệ thống kiểm soát nội bộ hữu hiệu là gì?",
        "difficulty": "Medium_QA"
      },
      {
        "question": "Việc lựa chọn và áp dụng chính sách kế toán nhất quán có tầm quan trọng như thế nào?",
        "difficulty": "Medium_SA"
      },
      {
        "question": "Nếu có sai lệch trọng yếu, Ban Tổng Giám đốc có trách nhiệm gì?",
        "difficulty": "Medium_QA"
      },
      {
        "question": "Phân tích ý nghĩa của việc lập báo cáo tài chính trên cơ sở hoạt động liên tục.",
        "difficulty": "Hard_SA"
      }
    ]
  },
  {
    "chunk_id": "4",
    "content": "Công ty: Công ty Cổ phần Khoáng sản và Vật liệu Xây dựng Lâm Đồng và Các Công ty Con\nMã cổ phiếu: Không có thông tin được cung cấp trong báo cáo.\nLoại báo cáo: Báo cáo tài chính hợp nhất đã được soát xét giữa niên độ\nThời gian: Cho kỳ kế toán 06 tháng kết thúc ngày 30 tháng 06 năm 2024 (phát hành ngày 26 tháng 08 năm 2024)\nÝ kiến kiểm toán: Chấp nhận toàn phần (dựa trên báo cáo soát xét)\n\nSection: Báo cáo của Ban Tổng Giám đốc (Trách nhiệm khác và Công bố Báo cáo Tài chính)\nLoại nội dung: Text\n\nBan Tổng Giám đốc xác nhận rằng Tập đoàn đã tuân thủ các yêu cầu nêu trên khi lập báo cáo tài chính hợp nhất.\nBan Tổng Giám đốc Tập đoàn chịu trách nhiệm đảm bảo rằng các sổ sách kế toán được ghi chép phù hợp và lưu giữ đầy đủ để phản ánh một cách hợp lý tình hình tài chính hợp nhất của Tập đoàn tại bất kỳ thời điểm nào và báo cáo tài chính hợp nhất được lập tuân thủ các Chuẩn mực kế toán và Chế độ kế toán doanh nghiệp Việt Nam cũng như các quy định hiện hành khác về kế toán tại Việt Nam. Ban Tổng Giám đốc Tập đoàn cũng chịu trách nhiệm đảm bảo an toàn tài sản của Tập đoàn và thực hiện những biện pháp thích hợp để ngăn chặn và phát hiện các hành vi gian lận và vi phạm khác.\n\nCÔNG BỐ BÁO CÁO TÀI CHÍNH\nBan Tổng Giám đốc Tập đoàn công bố rằng, báo cáo tài chính hợp nhất kèm theo phản ánh trung thực và hợp lý, trên các khía cạnh trọng yếu, tình hình tài chính hợp nhất của Tập đoàn vào ngày 30 tháng 06 năm 2024, kết quả hoạt động kinh doanh hợp nhất và tình hình lưu chuyển tiền tệ hợp nhất của kỳ kế toán kết thúc cùng ngày, phù hợp với các Chuẩn mực kế toán Việt Nam, Chế độ kế toán doanh nghiệp Việt Nam và các quy định hiện hành có liên quan tại Việt Nam.\n\nĐại diện cho Ban Tổng Giám đốc,\nNguyễn An Thái\nTổng Giám đốc\nLâm Đồng, ngày 26 tháng 08 năm 2024",
    "questions": [
      {
        "question": "Theo Ban Tổng Giám đốc, báo cáo tài chính hợp nhất có phản ánh trung thực và hợp lý tình hình tài chính của Tập đoàn không?",
        "difficulty": "Easy_QA"
      },
      {
        "question": "Ban Tổng Giám đốc có trách nhiệm gì đối với sổ sách kế toán của Tập đoàn?",
        "difficulty": "Medium_QA"
      },
      {
        "question": "Ngoài việc lập báo cáo, Ban Tổng Giám đốc còn có trách nhiệm gì khác liên quan đến tài sản của Tập đoàn?",
        "difficulty": "Medium_QA"
      },
      {
        "question": "Phân tích tầm quan trọng của việc ngăn chặn và phát hiện gian lận trong công tác quản lý tài chính doanh nghiệp.",
        "difficulty": "Hard_SA"
      },
      {
        "question": "Đánh giá mức độ tuân thủ các chuẩn mực kế toán của Tập đoàn dựa trên công bố của Ban Tổng Giám đốc.",
        "difficulty": "Hard_SA"
      }
    ]
  },
  {
    "chunk_id": "5",
    "content": "Công ty: Công ty Cổ phần Khoáng sản và Vật liệu Xây dựng Lâm Đồng và Các Công ty Con\nMã cổ phiếu: Không có thông tin được cung cấp trong báo cáo.\nLoại báo cáo: Báo cáo tài chính hợp nhất đã được soát xét giữa niên độ\nThời gian: Cho kỳ kế toán 06 tháng kết thúc ngày 30 tháng 06 năm 2024 (phát hành ngày 26 tháng 08 năm 2024)\nÝ kiến kiểm toán: Chấp nhận toàn phần (dựa trên báo cáo soát xét)\n\nSection: Báo cáo soát xét thông tin tài chính giữa niên độ (Phần 1 - Giới thiệu và Trách nhiệm Ban Tổng Giám đốc)\nLoại nội dung: Text\n\nBÁO CÁO SOÁT XÉT THÔNG TIN TÀI CHÍNH GIỮA NIÊN ĐỘ\n(Thực hiện bởi Công ty TNHH Kiểm toán - Tư vấn RSM Việt Nam)\n\nKính gửi: Các cổ đông, Hội đồng Quản trị, Ban Tổng Giám đốc CÔNG TY CỔ PHẦN KHOÁNG SẢN VÀ VẬT LIỆU XÂY DỰNG LÂM ĐỒNG\n\nChúng tôi đã soát xét báo cáo tài chính hợp nhất giữa niên độ kèm theo của Công ty Cổ phần Khoáng sản và Vật liệu Xây dựng Lâm Đồng (dưới đây gọi tắt là Công ty) và các công ty con (cùng với Công ty dưới đây gọi chung là Tập đoàn), được lập ngày 26 tháng 08 năm 2024, từ trang 05 đến trang 51, bao gồm Bảng cân đối kế toán hợp nhất tại ngày 30 tháng 06 năm 2024, Báo cáo kết quả hoạt động kinh doanh hợp nhất, Báo cáo lưu chuyển tiền tệ hợp nhất cho kỳ kế toán 06 tháng kết thúc cùng ngày và Bản thuyết minh báo cáo tài chính hợp nhất.\n\nTrách nhiệm của Ban Tổng Giám đốc\nBan Tổng Giám đốc Tập đoàn chịu trách nhiệm lập và trình bày trung thực và hợp lý báo cáo tài chính hợp nhất giữa niên độ theo Chuẩn mực kế toán, Chế độ kế toán doanh nghiệp Việt Nam và các quy định pháp lý có liên quan đến việc lập và trình bày báo cáo tài chính hợp nhất giữa niên độ và chịu trách nhiệm về kiểm soát nội bộ mà Ban Tổng Giám đốc xác định là cần thiết để đảm bảo cho việc lập và trình bày báo cáo tài chính hợp nhất giữa niên độ không có sai sót trọng yếu do gian lận hoặc nhầm lẫn.",
    "questions": [
      {
        "question": "Ai là đối tượng nhận báo cáo soát xét này?",
        "difficulty": "Easy_NER"
      },
      {
        "question": "Những báo cáo nào đã được soát xét bởi Công ty TNHH Kiểm toán - Tư vấn RSM Việt Nam?",
        "difficulty": "Easy_QA"
      },
      {
        "question": "Trách nhiệm của Ban Tổng Giám đốc trong việc lập báo cáo tài chính hợp nhất giữa niên độ là gì?",
        "difficulty": "Medium_QA"
      },
      {
        "question": "Báo cáo tài chính hợp nhất giữa niên độ phải tuân thủ các chuẩn mực và chế độ kế toán nào?",
        "difficulty": "Medium_QA"
      },
      {
        "question": "Kiểm soát nội bộ có vai trò gì trong việc đảm bảo tính trung thực của báo cáo tài chính?",
        "difficulty": "Medium_SA"
      },
      {
        "question": "Phân tích hậu quả nếu báo cáo tài chính hợp nhất giữa niên độ có sai sót trọng yếu do gian lận hoặc nhầm lẫn.",
        "difficulty": "Hard_SA"
      }
    ]
  },
  {
    "chunk_id": "6",
    "content": "Công ty: Công ty Cổ phần Khoáng sản và Vật liệu Xây dựng Lâm Đồng và Các Công ty Con\nMã cổ phiếu: Không có thông tin được cung cấp trong báo cáo.\nLoại báo cáo: Báo cáo tài chính hợp nhất đã được soát xét giữa niên độ\nThời gian: Cho kỳ kế toán 06 tháng kết thúc ngày 30 tháng 06 năm 2024 (phát hành ngày 26 tháng 08 năm 2024)\nÝ kiến kiểm toán: Chấp nhận toàn phần (dựa trên báo cáo soát xét)\n\nSection: Báo cáo soát xét thông tin tài chính giữa niên độ (Phần 2 - Trách nhiệm Kiểm toán viên)\nLoại nội dung: Text\n\nBÁO CÁO SOÁT XÉT THÔNG TIN TÀI CHÍNH GIỮA NIÊN ĐỘ TIẾP THEO\n\nTrách nhiệm của Kiểm toán viên\nTrách nhiệm của chúng tôi là đưa ra kết luận về báo cáo tài chính hợp nhất giữa niên độ dựa trên kết quả soát xét của chúng tôi. Chúng tôi đã thực hiện công việc soát xét theo Chuẩn mực Việt Nam về hợp đồng dịch vụ soát xét số 2410 - Soát xét thông tin tài chính hợp nhất giữa niên độ do kiểm toán viên độc lập của Tập đoàn thực hiện.\nCông việc soát xét thông tin tài chính hợp nhất giữa niên độ bao gồm việc thực hiện các cuộc phỏng vấn, chủ yếu là phỏng vấn những người chịu trách nhiệm về các vấn đề tài chính kế toán, và thực hiện thủ tục phân tích và các thủ tục soát xét khác. Một cuộc soát xét về cơ bản có phạm vi hẹp hơn một cuộc kiểm toán được thực hiện theo các Chuẩn mực kiểm toán Việt Nam và do vậy không cho phép chúng tôi đạt được sự đảm bảo rằng chúng tôi sẽ nhận biết được tất cả các vấn đề trọng yếu có thể được phát hiện trong một cuộc kiểm toán. Theo đó, chúng tôi không đưa ra ý kiến kiểm toán.",
    "questions": [
      {
        "question": "Mục tiêu của công việc soát xét của kiểm toán viên là gì?",
        "difficulty": "Easy_QA"
      },
      {
        "question": "Kiểm toán viên đã thực hiện công việc soát xét theo Chuẩn mực Việt Nam nào?",
        "difficulty": "Easy_QA"
      },
      {
        "question": "Công việc soát xét thông tin tài chính giữa niên độ bao gồm những hoạt động nào?",
        "difficulty": "Medium_QA"
      },
      {
        "question": "So sánh phạm vi của một cuộc soát xét và một cuộc kiểm toán theo Chuẩn mực kiểm toán Việt Nam.",
        "difficulty": "Medium_SA"
      },
      {
        "question": "Tại sao kiểm toán viên không đưa ra ý kiến kiểm toán trong một báo cáo soát xét?",
        "difficulty": "Medium_QA"
      },
      {
        "question": "Phân tích các hạn chế của một báo cáo soát xét so với một báo cáo kiểm toán đầy đủ.",
        "difficulty": "Hard_SA"
      }
    ]
  },
  {
    "chunk_id": "7",
    "content": "Công ty: Công ty Cổ phần Khoáng sản và Vật liệu Xây dựng Lâm Đồng và Các Công ty Con\nMã cổ phiếu: Không có thông tin được cung cấp trong báo cáo.\nLoại báo cáo: Báo cáo tài chính hợp nhất đã được soát xét giữa niên độ\nThời gian: Cho kỳ kế toán 06 tháng kết thúc ngày 30 tháng 06 năm 2024 (phát hành ngày 26 tháng 08 năm 2024)\nÝ kiến kiểm toán: Chấp nhận toàn phần (dựa trên báo cáo soát xét)\n\nSection: Báo cáo soát xét thông tin tài chính giữa niên độ (Phần 3 - Kết luận)\nLoại nội dung: Text\n\nBÁO CÁO SOÁT XÉT THÔNG TIN TÀI CHÍNH GIỮA NIÊN ĐỘ TIẾP THEO\n\nKết luận của kiểm toán viên\nCăn cứ trên kết quả soát xét của chúng tôi, chúng tôi không thấy có vấn đề gì khiến chúng tôi cho rằng báo cáo tài chính hợp nhất giữa niên độ đính kèm không phản ánh trung thực và hợp lý, trên các khía cạnh trọng yếu, tình hình tài chính hợp nhất của Công ty Cổ phần Khoáng sản và Vật liệu Xây dựng Lâm Đồng và các công ty con tại ngày 30 tháng 06 năm 2024, và kết quả hoạt động kinh doanh hợp nhất và lưu chuyển tiền tệ hợp nhất của Tập đoàn cho kỳ kế toán 06 tháng kết thúc cùng ngày phù hợp với Chuẩn mực Kế toán Việt Nam, Chế độ kế toán doanh nghiệp Việt Nam và các quy định pháp lý liên quan của Bộ Tài chính Việt Nam.\n\nGiám đốc\nGiấy chứng nhận đăng ký hành nghề kiểm toán số 3527-2021-026-1\nTheo Giấy ủy quyền số 11-2023/24/UQ-RSM ngày 01 tháng 10 năm 2023\nCông ty TNHH Kiểm toán - Tư vấn RSM Việt Nam\nTP. Hồ Chí Minh, ngày 26 tháng 08 năm 2024",
    "questions": [
      {
        "question": "Công ty Kiểm toán RSM Việt Nam có đưa ra ý kiến chấp nhận toàn phần cho báo cáo này không?",
        "difficulty": "Easy_QA"
      },
      {
        "question": "Báo cáo tài chính hợp nhất được soát xét phản ánh tình hình tài chính tại ngày nào?",
        "difficulty": "Easy_QA"
      },
      {
        "question": "Kết quả soát xét của kiểm toán viên có phát hiện vấn đề gì trọng yếu không?",
        "difficulty": "Medium_QA"
      },
      {
        "question": "Các chuẩn mực kế toán nào được áp dụng để lập báo cáo tài chính hợp nhất này?",
        "difficulty": "Medium_QA"
      },
      {
        "question": "Đánh giá mức độ tin cậy của thông tin tài chính dựa trên kết luận của kiểm toán viên trong báo cáo soát xét này.",
        "difficulty": "Hard_SA"
      }
    ]
  },
  {
    "chunk_id": "8",
    "content": "Công ty: Công ty Cổ phần Khoáng sản và Vật liệu Xây dựng Lâm Đồng và Các Công ty Con\nMã cổ phiếu: Không có thông tin được cung cấp trong báo cáo.\nLoại báo cáo: Báo cáo tài chính hợp nhất đã được soát xét giữa niên độ\nThời gian: Cho kỳ kế toán 06 tháng kết thúc ngày 30 tháng 06 năm 2024 (phát hành ngày 26 tháng 08 năm 2024)\nÝ kiến kiểm toán: Chấp nhận toàn phần (dựa trên báo cáo soát xét)\n\nSection: Báo cáo soát xét thông tin tài chính giữa niên độ (Phần 4 - Lưu ý về chuẩn mực quốc tế)\nLoại nội dung: Text\n\nNhư đã trình bày tại Mục 2.1 của Bản thuyết minh báo cáo tài chính hợp nhất, báo cáo tài chính hợp nhất kèm theo không nhằm phản ánh tình hình tài chính hợp nhất, kết quả hoạt động kinh doanh hợp nhất và tình hình lưu chuyển tiền tệ hợp nhất theo các nguyên tắc và thông lệ kế toán được chấp nhận chung tại các nước ngoài Việt Nam.",
    "questions": [
      {
        "question": "Báo cáo tài chính hợp nhất này có phản ánh theo các nguyên tắc kế toán được chấp nhận chung tại các nước ngoài Việt Nam không?",
        "difficulty": "Easy_QA"
      },
      {
        "question": "Mục nào trong Bản thuyết minh báo cáo tài chính hợp nhất đề cập đến lưu ý này?",
        "difficulty": "Easy_QA"
      },
      {
        "question": "Vì sao cần có lưu ý về sự khác biệt giữa chuẩn mực kế toán Việt Nam và quốc tế trong báo cáo tài chính?",
        "difficulty": "Medium_SA"
      },
      {
        "question": "Đối tượng nào cần đặc biệt lưu ý đến thông tin này khi đọc báo cáo?",
        "difficulty": "Medium_QA"
      },
      {
        "question": "Phân tích tác động tiềm tàng của sự khác biệt chuẩn mực kế toán đến khả năng so sánh báo cáo tài chính này với các công ty nước ngoài.",
        "difficulty": "Hard_SA"
      }
    ]
  },
  {
    "chunk_id": "9",
    "content": "Công ty: Công ty Cổ phần Khoáng sản và Vật liệu Xây dựng Lâm Đồng và Các Công ty Con\nMã cổ phiếu: Không có thông tin được cung cấp trong báo cáo.\nLoại báo cáo: Báo cáo tài chính hợp nhất đã được soát xét giữa niên độ\nThời gian: Tại ngày 30 tháng 06 năm 2024\nÝ kiến kiểm toán: Chấp nhận toàn phần (dựa trên báo cáo soát xét)\n\nSection: Bảng cân đối kế toán hợp nhất (Phần A - Tài sản ngắn hạn, mục I và II)\nLoại nội dung: Bảng\n| Chỉ tiêu | Mã số | Thuyết minh | Tại ngày 30/06/2024 | Tại ngày 01/01/2024 |\n|---|---|---|---|---|\n| A. TÀI SẢN NGẮN HẠN | 100 | | 403.539.453.527 | 403.101.143.434 |\n| I. Tiền và các khoản tương đương tiền | 110 | 4.1 | 55.916.108.451 | 71.485.359.897 |\n| 1. Tiền | 111 | | 36.916.108.451 | 46.485.359.897 |\n| 2. Các khoản tương đương tiền | 112 | | 19.000.000.000 | 25.000.000.000 |\n| II. Các khoản phải thu ngắn hạn | 130 | | 239.111.761.084 | 215.573.201.719 |\n| 1. Phải thu ngắn hạn của khách hàng | 131 | 4.2 | 88.711.157.899 | 76.393.558.224 |\n| 2. Trả trước cho người bán ngắn hạn | 132 | 4.3 | 72.922.411.371 | 75.041.010.562 |\n| 3. Phải thu ngắn hạn khác | 136 | 4.4 | 103.968.083.983 | 90.992.697.961 |\n| 4. Dự phòng phải thu ngắn hạn khó đòi | 137 | 4.5 | (26.489.892.169) | (26.854.065.028) |",
    "questions": [
      {
        "question": "Tổng tài sản ngắn hạn tại ngày 30/06/2024 là bao nhiêu?",
        "difficulty": "Easy_QA"
      },
      {
        "question": "Tiền và các khoản tương đương tiền tại ngày 01/01/2024 là bao nhiêu?",
        "difficulty": "Easy_QA"
      },
      {
        "question": "Số dư các khoản phải thu ngắn hạn của khách hàng thay đổi như thế nào từ đầu năm đến cuối quý?",
        "difficulty": "Medium_QA"
      },
      {
        "question": "Khoản mục nào chiếm tỷ trọng lớn nhất trong các khoản phải thu ngắn hạn tại ngày 30/06/2024?",
        "difficulty": "Medium_QA"
      },
      {
        "question": "Đánh giá mức độ biến động của tiền và các khoản tương đương tiền từ đầu năm đến cuối quý.",
        "difficulty": "Medium_SA"
      },
      {
        "question": "Phân tích rủi ro tiềm tàng từ sự tăng lên của các khoản phải thu ngắn hạn khác.",
        "difficulty": "Hard_SA"
      },
      {
        "question": "Tính tỷ lệ dự phòng phải thu ngắn hạn khó đòi trên tổng các khoản phải thu ngắn hạn tại 30/06/2024.",
        "difficulty": "Hard_QA"
      }
    ]
  },
  {
    "chunk_id": "10",
    "content": "Công ty: Công ty Cổ phần Khoáng sản và Vật liệu Xây dựng Lâm Đồng và Các Công ty Con\nMã cổ phiếu: Không có thông tin được cung cấp trong báo cáo.\nLoại báo cáo: Báo cáo tài chính hợp nhất đã được soát xét giữa niên độ\nThời gian: Tại ngày 30 tháng 06 năm 2024\nÝ kiến kiểm toán: Chấp nhận toàn phần (dựa trên báo cáo soát xét)\n\nSection: Bảng cân đối kế toán hợp nhất (Phần A - Tài sản ngắn hạn, mục III và IV)\nLoại nội dung: Bảng\n| Chỉ tiêu | Mã số | Thuyết minh | Tại ngày 30/06/2024 | Tại ngày 01/01/2024 |\n|---|---|---|---|---|\n| III. Hàng tồn kho | 140 | 4.6 | 106.245.771.694 | 113.739.288.576 |\n| 1. Hàng tồn kho | 141 | | 107.796.576.563 | 115.290.093.445 |\n| 2. Dự phòng giảm giá hàng tồn kho | 149 | | (1.550.804.869) | (1.550.804.869) |\n| IV. Tài sản ngắn hạn khác | 150 | | 2.265.812.298 | 2.303.293.242 |\n| 1. Chi phí trả trước ngắn hạn | 151 | | 455.587.743 | - |\n| 2. Thuế GTGT được khấu trừ | 152 | 4.13 | 749.896.551 | 103.827.383 |\n| 3. Thuế và các khoản khác phải thu Nhà nước | 153 | 4.13 | 1.060.328.004 | 2.199.465.859 |",
    "questions": [
      {
        "question": "Tổng giá trị hàng tồn kho tại ngày 30/06/2024 là bao nhiêu?",
        "difficulty": "Easy_QA"
      },
      {
        "question": "Thuế GTGT được khấu trừ tại ngày 30/06/2024 là bao nhiêu?",
        "difficulty": "Easy_QA"
      },
      {
        "question": "So sánh hàng tồn kho cuối quý với đầu năm, xu hướng thay đổi như thế nào?",
        "difficulty": "Medium_QA"
      },
      {
        "question": "Chi phí trả trước ngắn hạn tại ngày 01/01/2024 là bao nhiêu?",
        "difficulty": "Easy_QA"
      },
      {
        "question": "Đánh giá sự thay đổi trong các khoản phải thu Nhà nước từ đầu năm đến cuối quý.",
        "difficulty": "Medium_SA"
      },
      {
        "question": "Phân tích ý nghĩa của việc dự phòng giảm giá hàng tồn kho giữ nguyên giữa hai kỳ.",
        "difficulty": "Hard_SA"
      },
      {
        "question": "Nếu chi phí trả trước ngắn hạn không có số liệu vào đầu năm, điều này có thể gợi ý gì về hoạt động của công ty?",
        "difficulty": "Hard_SA"
      }
    ]
  },
  {
    "chunk_id": "11",
    "content": "Công ty: Công ty Cổ phần Khoáng sản và Vật liệu Xây dựng Lâm Đồng và Các Công ty Con\nMã cổ phiếu: Không có thông tin được cung cấp trong báo cáo.\nLoại báo cáo: Báo cáo tài chính hợp nhất đã được soát xét giữa niên độ\nThời gian: Tại ngày 30 tháng 06 năm 2024\nÝ kiến kiểm toán: Chấp nhận toàn phần (dựa trên báo cáo soát xét)\n\nSection: Bảng cân đối kế toán hợp nhất (Phần B - Tài sản dài hạn, mục I và II.1)\nLoại nội dung: Bảng\n| Chỉ tiêu | Mã số | Thuyết minh | Tại ngày 30/06/2024 | Tại ngày 01/01/2024 |\n|---|---|---|---|---|\n| B. TÀI SẢN DÀI HẠN | 200 | | 369.822.424.806 | 366.774.571.587 |\n| I. Các khoản phải thu dài hạn | 210 | | 3.147.443.292 | 3.085.352.449 |\n| 1. Phải thu dài hạn khác | 216 | 4.4 | 3.147.443.292 | 3.085.352.449 |\n| II. Tài sản cố định | 220 | | 332.261.031.163 | 307.738.921.969 |\n| 1. Tài sản cố định hữu hình | 221 | 4.8 | 317.915.882.067 | 293.250.734.103 |\n| - Nguyên giá | 222 | | 827.163.382.315 | 767.417.535.877 |\n| - Giá trị hao mòn lũy kế | 223 | | (509.247.500.248) | (474.166.801.774) |",
    "questions": [
      {
        "question": "Tổng tài sản dài hạn tại ngày 30/06/2024 là bao nhiêu?",
        "difficulty": "Easy_QA"
      },
      {
        "question": "Nguyên giá tài sản cố định hữu hình tại ngày 30/06/2024 là bao nhiêu?",
        "difficulty": "Easy_QA"
      },
      {
        "question": "So sánh giá trị hao mòn lũy kế của tài sản cố định hữu hình giữa hai kỳ.",
        "difficulty": "Medium_QA"
      },
      {
        "question": "Các khoản phải thu dài hạn khác thay đổi như thế nào từ đầu năm đến cuối quý?",
        "difficulty": "Medium_QA"
      },
      {
        "question": "Đánh giá mức độ đầu tư vào tài sản cố định hữu hình của công ty trong kỳ.",
        "difficulty": "Medium_SA"
      },
      {
        "question": "Phân tích tác động của sự tăng nguyên giá tài sản cố định hữu hình đến khả năng sinh lời dài hạn của công ty.",
        "difficulty": "Hard_SA"
      },
      {
        "question": "Dựa trên các chỉ số tài sản dài hạn, nhận định chiến lược kinh doanh của công ty.",
        "difficulty": "Hard_SA"
      }
    ]
  },
  {
    "chunk_id": "12",
    "content": "Công ty: Công ty Cổ phần Khoáng sản và Vật liệu Xây dựng Lâm Đồng và Các Công ty Con\nMã cổ phiếu: Không có thông tin được cung cấp trong báo cáo.\nLoại báo cáo: Báo cáo tài chính hợp nhất đã được soát xét giữa niên độ\nThời gian: Tại ngày 30 tháng 06 năm 2024\nÝ kiến kiểm toán: Chấp nhận toàn phần (dựa trên báo cáo soát xét)\n\nSection: Bảng cân đối kế toán hợp nhất (Phần B - Tài sản dài hạn, mục II.2, III, IV và Tổng Cộng Tài sản)\nLoại nội dung: Bảng\n| Chỉ tiêu | Mã số | Thuyết minh | Tại ngày 30/06/2024 | Tại ngày 01/01/2024 |\n|---|---|---|---|---|\n| 2. Tài sản cố định vô hình | 227 | 4.9 | 14.345.149.096 | 14.488.187.866 |\n| - Nguyên giá | 228 | | 19.929.726.974 | 19.929.726.974 |\n| - Giá trị hao mòn lũy kế | 229 | | (5.584.577.878) | (5.441.539.108) |\n| III. Tài sản dở dang dài hạn | 240 | | 19.094.104.415 | 38.750.707.333 |\n| 1. Chi phí xây dựng cơ bản dở dang | 242 | 4.7 | 19.094.104.415 | 38.750.707.333 |\n| IV. Tài sản dài hạn khác | 260 | | 15.319.845.936 | 17.199.589.836 |\n| 1. Chi phí trả trước dài hạn | 261 | 4.10 | 14.997.135.741 | 15.497.653.076 |\n| 2. Tài sản thuế thu nhập hoãn lại | 262 | 4.17 | 322.710.195 | 1.701.936.760 |\n| TỔNG CỘNG TÀI SẢN | 270 | | 773.361.878.333 | 769.875.715.021 |",
    "questions": [
      {
        "question": "Giá trị còn lại của tài sản cố định vô hình tại ngày 30/06/2024 là bao nhiêu?",
        "difficulty": "Easy_QA"
      },
      {
        "question": "Tổng tài sản của công ty tại ngày 30/06/2024 là bao nhiêu?",
        "difficulty": "Easy_QA"
      },
      {
        "question": "Sự thay đổi của chi phí xây dựng cơ bản dở dang từ đầu năm đến cuối quý có ý nghĩa gì?",
        "difficulty": "Medium_QA"
      },
      {
        "question": "So sánh giá trị tài sản thuế thu nhập hoãn lại giữa hai kỳ và giải thích sự thay đổi.",
        "difficulty": "Medium_QA"
      },
      {
        "question": "Đánh giá hiệu quả quản lý chi phí trả trước dài hạn của công ty.",
        "difficulty": "Medium_SA"
      },
      {
        "question": "Phân tích tác động của việc giảm tài sản dở dang dài hạn đến cấu trúc tài sản của công ty.",
        "difficulty": "Hard_SA"
      },
      {
        "question": "Nêu rủi ro tiềm tàng nếu tài sản thuế thu nhập hoãn lại tiếp tục giảm.",
        "difficulty": "Hard_SA"
      }
    ]
  },
  {
    "chunk_id": "13",
    "content": "Công ty: Công ty Cổ phần Khoáng sản và Vật liệu Xây dựng Lâm Đồng và Các Công ty Con\nMã cổ phiếu: Không có thông tin được cung cấp trong báo cáo.\nLoại báo cáo: Báo cáo tài chính hợp nhất đã được soát xét giữa niên độ\nThời gian: Tại ngày 30 tháng 06 năm 2024\nÝ kiến kiểm toán: Chấp nhận toàn phần (dựa trên báo cáo soát xét)\n\nSection: Bảng cân đối kế toán hợp nhất (Phần C - Nợ ngắn hạn)\nLoại nội dung: Bảng\n| Chỉ tiêu | Mã số | Thuyết minh | Tại ngày 30/06/2024 | Tại ngày 01/01/2024 |\n|---|---|---|---|---|\n| C. NỢ PHẢI TRẢ | 300 | | 155.904.514.559 | 169.308.485.914 |\n| I. Nợ ngắn hạn | 310 | | 121.918.014.559 | 129.321.985.914 |\n| 1. Phải trả người bán ngắn hạn | 311 | 4.11 | 30.457.210.720 | 27.673.443.826 |\n| 2. Người mua trả tiền trước ngắn hạn | 312 | 4.12 | 4.667.084.878 | 4.086.056.943 |\n| 3. Thuế và các khoản phải nộp Nhà nước | 313 | 4.13 | 7.521.355.797 | 6.826.074.195 |\n| 4. Phải trả người lao động | 314 | | 20.044.098.653 | 35.012.413.226 |\n| 5. Chi phí phải trả ngắn hạn | 315 | 4.14 | 3.562.406.223 | 3.153.604.226 |\n| 6. Phải trả ngắn hạn khác | 319 | 4.15 | 1.468.749.548 | 1.738.097.824 |\n| 7. Vay và nợ thuê tài chính ngắn hạn | 320 | 4.16 | 53.342.529.286 | 49.977.716.220 |\n| 8. Quỹ khen thưởng, phúc lợi | 322 | | 854.579.454 | 854.579.454 |",
    "questions": [
      {
        "question": "Tổng nợ phải trả tại ngày 30/06/2024 là bao nhiêu?",
        "difficulty": "Easy_QA"
      },
      {
        "question": "Nợ ngắn hạn tại ngày 30/06/2024 là bao nhiêu?",
        "difficulty": "Easy_QA"
      },
      {
        "question": "Khoản mục nào có sự thay đổi lớn nhất trong nợ ngắn hạn từ đầu năm đến cuối quý?",
        "difficulty": "Medium_QA"
      },
      {
        "question": "Vay và nợ thuê tài chính ngắn hạn tại ngày 30/06/2024 là bao nhiêu?",
        "difficulty": "Easy_QA"
      },
      {
        "question": "Đánh giá khả năng thanh toán nợ ngắn hạn của công ty dựa trên số liệu này.",
        "difficulty": "Medium_SA"
      },
      {
        "question": "Phân tích tác động của sự giảm khoản phải trả người lao động đến dòng tiền và hoạt động của công ty.",
        "difficulty": "Hard_SA"
      },
      {
        "question": "Nếu nợ ngắn hạn cao hơn tài sản ngắn hạn, điều này có thể báo hiệu rủi ro gì?",
        "difficulty": "Hard_SA"
      }
    ]
  },
  {
    "chunk_id": "14",
    "content": "Công ty: Công ty Cổ phần Khoáng sản và Vật liệu Xây dựng Lâm Đồng và Các Công ty Con\nMã cổ phiếu: Không có thông tin được cung cấp trong báo cáo.\nLoại báo cáo: Báo cáo tài chính hợp nhất đã được soát xét giữa niên độ\nThời gian: Tại ngày 30 tháng 06 năm 2024\nÝ kiến kiểm toán: Chấp nhận toàn phần (dựa trên báo cáo soát xét)\n\nSection: Bảng cân đối kế toán hợp nhất (Phần C - Nợ dài hạn)\nLoại nội dung: Bảng\n| Chỉ tiêu | Mã số | Thuyết minh | Tại ngày 30/06/2024 | Tại ngày 01/01/2024 |\n|---|---|---|---|---|\n| C. NỢ PHẢI TRẢ | 300 | | 155.904.514.559 | 169.308.485.914 |\n| II. Nợ dài hạn | 330 | | 33.986.500.000 | 39.986.500.000 |\n| 1. Vay và nợ thuê tài chính dài hạn | 338 | 4.16 | 33.000.000.000 | 39.000.000.000 |\n| 2. Dự phòng phải trả dài hạn | 342 | | 986.500.000 | 986.500.000 |",
    "questions": [
      {
        "question": "Tổng nợ dài hạn tại ngày 30/06/2024 là bao nhiêu?",
        "difficulty": "Easy_QA"
      },
      {
        "question": "Vay và nợ thuê tài chính dài hạn tại ngày 01/01/2024 là bao nhiêu?",
        "difficulty": "Easy_QA"
      },
      {
        "question": "So sánh nợ dài hạn giữa hai kỳ, có xu hướng tăng hay giảm?",
        "difficulty": "Medium_QA"
      },
      {
        "question": "Khoản mục dự phòng phải trả dài hạn có thay đổi không?",
        "difficulty": "Medium_QA"
      },
      {
        "question": "Đánh giá mức độ phụ thuộc vào nợ dài hạn của công ty.",
        "difficulty": "Medium_SA"
      },
      {
        "question": "Phân tích rủi ro khi vay và nợ thuê tài chính dài hạn giảm, nhưng tổng nợ phải trả không giảm tương ứng.",
        "difficulty": "Hard_SA"
      },
      {
        "question": "Dựa vào cơ cấu nợ dài hạn, nhận định chiến lược tài chính của công ty.",
        "difficulty": "Hard_SA"
      }
    ]
  },
  {
    "chunk_id": "15",
    "content": "Công ty: Công ty Cổ phần Khoáng sản và Vật liệu Xây dựng Lâm Đồng và Các Công ty Con\nMã cổ phiếu: Không có thông tin được cung cấp trong báo cáo.\nLoại báo cáo: Báo cáo tài chính hợp nhất đã được soát xét giữa niên độ\nThời gian: Tại ngày 30 tháng 06 năm 2024\nÝ kiến kiểm toán: Chấp nhận toàn phần (dựa trên báo cáo soát xét)\n\nSection: Bảng cân đối kế toán hợp nhất (Phần D - Vốn chủ sở hữu)\nLoại nội dung: Bảng\n| Chỉ tiêu | Mã số | Thuyết minh | Tại ngày 30/06/2024 | Tại ngày 01/01/2024 |\n|---|---|---|---|---|\n| D. VỐN CHỦ SỞ HỮU | 400 | | 617.457.363.774 | 600.567.229.107 |\n| I. Vốn chủ sở hữu | 410 | 4.18 | 617.457.363.774 | 600.567.229.107 |\n| 1. Vốn góp của chủ sở hữu | 411 | | 200.000.000.000 | 200.000.000.000 |\n| Cổ phiếu phổ thông có quyền biểu quyết | 411a | | 200.000.000.000 | 200.000.000.000 |\n| 2. Quỹ đầu tư phát triển | 418 | | 293.769.438.455 | 293.769.438.455 |\n| 3. Lợi nhuận sau thuế chưa phân phối | 421 | | 119.277.571.530 | 102.283.196.478 |\n| 4. Lợi ích cổ đông không kiểm soát | 429 | | 4.410.353.789 | 4.514.594.174 |\n| TỔNG CỘNG NGUỒN VỐN | 440 | | 773.361.878.333 | 769.875.715.021 |",
    "questions": [
      {
        "question": "Tổng vốn chủ sở hữu tại ngày 30/06/2024 là bao nhiêu?",
        "difficulty": "Easy_QA"
      },
      {
        "question": "Lợi nhuận sau thuế chưa phân phối tại ngày 01/01/2024 là bao nhiêu?",
        "difficulty": "Easy_QA"
      },
      {
        "question": "Vốn góp của chủ sở hữu có thay đổi giữa hai kỳ không?",
        "difficulty": "Medium_QA"
      },
      {
        "question": "So sánh lợi nhuận sau thuế chưa phân phối giữa hai kỳ và nhận xét về xu hướng.",
        "difficulty": "Medium_QA"
      },
      {
        "question": "Đánh giá cấu trúc vốn của công ty dựa trên tỷ lệ giữa vốn góp của chủ sở hữu và tổng vốn chủ sở hữu.",
        "difficulty": "Medium_SA"
      },
      {
        "question": "Tính tỷ lệ vốn chủ sở hữu trên tổng nguồn vốn tại ngày 30/06/2024 và nhận định về đòn bẩy tài chính.",
        "difficulty": "Hard_QA"
      },
      {
        "question": "Phân tích ý nghĩa của sự giảm lợi ích cổ đông không kiểm soát đối với công ty mẹ.",
        "difficulty": "Hard_SA"
      }
    ]
  },
  {
    "chunk_id": "16",
    "content": "Công ty: Công ty Cổ phần Khoáng sản và Vật liệu Xây dựng Lâm Đồng và Các Công ty Con\nMã cổ phiếu: Không có thông tin được cung cấp trong báo cáo.\nLoại báo cáo: Báo cáo tài chính hợp nhất đã được soát xét giữa niên độ\nThời gian: Cho kỳ kế toán 06 tháng kết thúc ngày 30 tháng 06 năm 2024 (phát hành ngày 26 tháng 08 năm 2024)\nÝ kiến kiểm toán: Chấp nhận toàn phần (dựa trên báo cáo soát xét)\n\nSection: Báo cáo kết quả hoạt động kinh doanh hợp nhất (Phần 1)\nLoại nội dung: Bảng\n| CHỈ TIÊU | Mã số | Thuyết minh | Kỳ này | Kỳ trước |\n|---|---|---|---|---|\n| Doanh thu bán hàng và cung cấp dịch vụ | 01 | 5.1 | 419.370.267.717 | 521.472.219.504 |\n| Doanh thu thuần về bán hàng và cung cấp dịch vụ | 10 | | 419.370.267.717 | 521.472.219.504 |\n| Giá vốn hàng bán | 11 | 5.2 | 318.809.183.832 | 369.781.987.100 |\n| Lợi nhuận gộp về bán hàng và cung cấp dịch vụ | 20 | | 100.561.083.885 | 151.690.232.404 |\n| Doanh thu hoạt động tài chính | 21 | 5.3 | 328.155.893 | 592.851.077 |\n| Chi phí tài chính | 22 | 5.4 | 2.325.083.410 | 1.937.417.553 |\n| Trong đó: Chi phí lãi vay | 23 | | 2.126.046.076 | 1.770.999.980 |\n| Chi phí bán hàng | 25 | 5.5 | 3.146.250.410 | 1.605.864.092 |\n| Chi phí quản lý doanh nghiệp | 26 | 5.6 | 35.143.861.911 | 33.747.420.802 |\n| Lợi nhuận thuần từ hoạt động kinh doanh | 30 | | 60.274.044.047 | 114.992.381.034 |",
    "questions": [
      {
        "question": "Doanh thu thuần về bán hàng và cung cấp dịch vụ kỳ này là bao nhiêu?",
        "difficulty": "Easy_QA"
      },
      {
        "question": "Lợi nhuận gộp kỳ trước là bao nhiêu VND?",
        "difficulty": "Easy_QA"
      },
      {
        "question": "So sánh doanh thu bán hàng và cung cấp dịch vụ kỳ này với kỳ trước.",
        "difficulty": "Medium_QA"
      },
      {
        "question": "Chi phí tài chính kỳ này thay đổi như thế nào so với kỳ trước?",
        "difficulty": "Medium_QA"
      },
      {
        "question": "Tính tỷ suất lợi nhuận gộp kỳ này.",
        "difficulty": "Medium_QA"
      },
      {
        "question": "Đánh giá hiệu quả hoạt động kinh doanh của công ty dựa trên lợi nhuận thuần từ hoạt động kinh doanh.",
        "difficulty": "Hard_SA"
      },
      {
        "question": "Phân tích tác động của sự tăng chi phí bán hàng đến lợi nhuận của công ty.",
        "difficulty": "Hard_SA"
      }
    ]
  },
  {
    "chunk_id": "17",
    "content": "Công ty: Công ty Cổ phần Khoáng sản và Vật liệu Xây dựng Lâm Đồng và Các Công ty Con\nMã cổ phiếu: Không có thông tin được cung cấp trong báo cáo.\nLoại báo cáo: Báo cáo tài chính hợp nhất đã được soát xét giữa niên độ\nThời gian: Cho kỳ kế toán 06 tháng kết thúc ngày 30 tháng 06 năm 2024 (phát hành ngày 26 tháng 08 năm 2024)\nÝ kiến kiểm toán: Chấp nhận toàn phần (dựa trên báo cáo soát xét)\n\nSection: Báo cáo kết quả hoạt động kinh doanh hợp nhất (Phần 2)\nLoại nội dung: Bảng\n| CHỈ TIÊU | Mã số | Thuyết minh | Kỳ này | Kỳ trước |\n|---|---|---|---|---|\n| Thu nhập khác | 31 | 5.7 | 190.590.333 | 3.136.148.380 |\n| Chi phí khác | 32 | 5.8 | 720.129.276 | 1.676.709.980 |\n| Lợi nhuận khác | 40 | | (529.538.943) | 1.459.438.400 |\n| Tổng lợi nhuận kế toán trước thuế | 50 | | 59.744.505.104 | 116.451.819.434 |\n| Chi phí thuế TNDN hiện hành | 51 | 5.10 | 11.298.443.872 | 25.174.033.984 |\n| Chi phí thuế TNDN hoãn lại | 52 | 5.11 | 1.379.226.565 | 133.132.850 |\n| Lợi nhuận sau thuế thu nhập doanh nghiệp | 60 | | 47.066.834.667 | 91.144.652.600 |\n| Lợi nhuận sau thuế của công ty mẹ | 61 | | 46.994.375.052 | 91.025.626.716 |\n| Lợi nhuận sau thuế của cổ đông không kiểm soát | 62 | | 72.459.615 | 119.025.884 |\n| Lãi cơ bản trên cổ phiếu | 70 | 4.18.4 | 2.350 | 4.551 |\n| Lãi suy giảm trên cổ phiếu | 71 | 4.18.4 | 2.350 | 4.551 |",
    "questions": [
      {
        "question": "Tổng lợi nhuận kế toán trước thuế kỳ này là bao nhiêu?",
        "difficulty": "Easy_QA"
      },
      {
        "question": "Lợi nhuận sau thuế của công ty mẹ kỳ này là bao nhiêu?",
        "difficulty": "Easy_QA"
      },
      {
        "question": "So sánh Lãi cơ bản trên cổ phiếu kỳ này với kỳ trước.",
        "difficulty": "Medium_QA"
      },
      {
        "question": "Tổng lợi nhuận khác kỳ này là bao nhiêu?",
        "difficulty": "Easy_QA"
      },
      {
        "question": "Tính tỷ suất lợi nhuận sau thuế của công ty mẹ trên tổng lợi nhuận kế toán trước thuế kỳ này.",
        "difficulty": "Medium_QA"
      },
      {
        "question": "Phân tích tác động của chi phí thuế TNDN hoãn lại đến lợi nhuận sau thuế của công ty.",
        "difficulty": "Hard_SA"
      },
      {
        "question": "Đánh giá triển vọng đầu tư vào cổ phiếu công ty dựa trên lãi cơ bản và suy giảm trên cổ phiếu.",
        "difficulty": "Hard_SA"
      }
    ]
  },
  {
    "chunk_id": "18",
    "content": "Công ty: Công ty Cổ phần Khoáng sản và Vật liệu Xây dựng Lâm Đồng và Các Công ty Con\nMã cổ phiếu: Không có thông tin được cung cấp trong báo cáo.\nLoại báo cáo: Báo cáo tài chính hợp nhất đã được soát xét giữa niên độ\nThời gian: Cho kỳ kế toán 06 tháng kết thúc ngày 30 tháng 06 năm 2024 (phát hành ngày 26 tháng 08 năm 2024)\nÝ kiến kiểm toán: Chấp nhận toàn phần (dựa trên báo cáo soát xét)\n\nSection: Báo cáo lưu chuyển tiền tệ hợp nhất (Phần I - Lưu chuyển tiền từ hoạt động kinh doanh, Điều chỉnh)\nLoại nội dung: Bảng\n| CHỈ TIÊU | Mã số | Thuyết minh | Kỳ này | Kỳ trước |\n|---|---|---|---|---|\n| I. LƯU CHUYỂN TIỀN TỪ HOẠT ĐỘNG KINH DOANH | | | | |\n| 1. Lợi nhuận trước thuế | 01 | | 59.744.505.104 | 116.451.819.434 |\n| 2. Điều chỉnh cho các khoản | | | | |\n| Khấu hao TSCĐ và BĐSĐT | 02 | 5.9 | 36.645.408.791 | 39.600.083.901 |\n| Các khoản dự phòng | 03 | | 364.172.859 | 164.839.403 |\n| Lỗ chênh lệch tỷ giá hối đoái do đánh giá lại các khoản mục tiền tệ có gốc ngoại tệ | 04 | | 41.473.930 | 1.192.911 |\n| Lãi, lỗ từ hoạt động đầu tư | 05 | | (335.073.619) | (3.284.922.352) |\n| Chi phí lãi vay | 06 | 5.4 | 2.126.046.076 | 1.770.999.980 |",
    "questions": [
      {
        "question": "Lợi nhuận trước thuế kỳ này là bao nhiêu?",
        "difficulty": "Easy_QA"
      },
      {
        "question": "Chi phí khấu hao TSCĐ và BĐSĐT kỳ trước là bao nhiêu VND?",
        "difficulty": "Easy_QA"
      },
      {
        "question": "Khoản điều chỉnh nào có giá trị lớn nhất trong kỳ này?",
        "difficulty": "Medium_QA"
      },
      {
        "question": "So sánh chi phí lãi vay kỳ này với kỳ trước, thay đổi như thế nào?",
        "difficulty": "Medium_QA"
      },
      {
        "question": "Giải thích vai trò của các khoản điều chỉnh trong việc chuyển đổi lợi nhuận trước thuế sang lưu chuyển tiền tệ từ hoạt động kinh doanh.",
        "difficulty": "Medium_SA"
      },
      {
        "question": "Phân tích tác động của lỗ chênh lệch tỷ giá hối đoái đến lưu chuyển tiền tệ.",
        "difficulty": "Hard_SA"
      },
      {
        "question": "Đánh giá mức độ ảnh hưởng của các khoản điều chỉnh không dùng tiền mặt đến dòng tiền hoạt động.",
        "difficulty": "Hard_SA"
      }
    ]
  },
  {
    "chunk_id": "19",
    "content": "Công ty: Công ty Cổ phần Khoáng sản và Vật liệu Xây dựng Lâm Đồng và Các Công ty Con\nMã cổ phiếu: Không có thông tin được cung cấp trong báo cáo.\nLoại báo cáo: Báo cáo tài chính hợp nhất đã được soát xét giữa niên độ\nThời gian: Cho kỳ kế toán 06 tháng kết thúc ngày 30 tháng 06 năm 2024 (phát hành ngày 26 tháng 08 năm 2024)\nÝ kiến kiểm toán: Chấp nhận toàn phần (dựa trên báo cáo soát xét)\n\nSection: Báo cáo lưu chuyển tiền tệ hợp nhất (Phần I - Lưu chuyển tiền từ hoạt động kinh doanh, Lưu chuyển tiền thuần)\nLoại nội dung: Bảng\n| CHỈ TIÊU | Mã số | Thuyết minh | Kỳ này | Kỳ trước |\n|---|---|---|---|---|\n| 3. Lợi nhuận từ hoạt động kinh doanh | 08 | | 97.858.187.423 | 154.701.627.455 |\n| Tăng các khoản phải thu | 09 | | (22.750.439.911) | (100.581.788.466) |\n| Giảm hàng tồn kho | 10 | | 7.493.516.882 | 5.950.587.017 |\n| Tăng, giảm các khoản phải trả không kể lãi vay phải trả, thuế thu nhập doanh nghiệp phải nộp | 11 | | 17.472.950.873 | 66.600.377.142 |\n| Tăng, giảm chi phí trả trước | 12 | | (44.929.592) | (216.242.445) |\n| Tiền lãi vay đã trả | 14 | | (2.263.010.458) | (1.981.802.897) |\n| Thuế thu nhập doanh nghiệp đã nộp | 15 | 4.13 | (10.807.487.758) | (30.928.315.120) |\n| Tiền chi khác từ hoạt động kinh doanh | 17 | | - | (2.000.000) |\n| Lưu chuyển tiền thuần từ hoạt động kinh doanh | 20 | | 52.102.744.897 | 93.542.442.686 |",
    "questions": [
      {
        "question": "Lưu chuyển tiền thuần từ hoạt động kinh doanh kỳ này là bao nhiêu?",
        "difficulty": "Easy_QA"
      },
      {
        "question": "Số tiền thuế thu nhập doanh nghiệp đã nộp kỳ trước là bao nhiêu?",
        "difficulty": "Easy_QA"
      },
      {
        "question": "Sự thay đổi về tăng các khoản phải thu từ kỳ trước sang kỳ này có ý nghĩa gì?",
        "difficulty": "Medium_QA"
      },
      {
        "question": "So sánh lưu chuyển tiền thuần từ hoạt động kinh doanh giữa hai kỳ và nhận xét về xu hướng.",
        "difficulty": "Medium_QA"
      },
      {
        "question": "Đánh giá ảnh hưởng của việc giảm hàng tồn kho đến dòng tiền hoạt động.",
        "difficulty": "Medium_SA"
      },
      {
        "question": "Phân tích tác động của sự thay đổi các khoản phải trả đến khả năng tạo tiền từ hoạt động kinh doanh.",
        "difficulty": "Hard_SA"
      },
      {
        "question": "Nếu lưu chuyển tiền thuần từ hoạt động kinh doanh giảm mạnh, điều này có thể báo hiệu rủi ro gì cho công ty?",
        "difficulty": "Hard_SA"
      }
    ]
  },
  {
    "chunk_id": "20",
    "content": "Công ty: Công ty Cổ phần Khoáng sản và Vật liệu Xây dựng Lâm Đồng và Các Công ty Con\nMã cổ phiếu: Không có thông tin được cung cấp trong báo cáo.\nLoại báo cáo: Báo cáo tài chính hợp nhất đã được soát xét giữa niên độ\nThời gian: Cho kỳ kế toán 06 tháng kết thúc ngày 30 tháng 06 năm 2024 (phát hành ngày 26 tháng 08 năm 2024)\nÝ kiến kiểm toán: Chấp nhận toàn phần (dựa trên báo cáo soát xét)\n\nSection: Báo cáo lưu chuyển tiền tệ hợp nhất (Phần II - Lưu chuyển tiền từ hoạt động đầu tư)\nLoại nội dung: Bảng\n| CHỈ TIÊU | Mã số | Thuyết minh | Kỳ này | Kỳ trước |\n|---|---|---|---|---|\n| II. LƯU CHUYỂN TIỀN TỪ HOẠT ĐỘNG ĐẦU TƯ | | | | |\n| 1. Tiền chi để mua sắm, xây dựng TSCĐ và các tài sản dài hạn khác | 21 | | (35.207.250.638) | (124.946.177.051) |\n| 2. Tiền thu từ thanh lý, nhượng bán TSCĐ và các tài sản dài hạn khác | 22 | | 122.887.233 | 2.597.000.000 |\n| 3. Tiền thu lãi cho vay, cổ tức và lợi nhuận được chia | 27 | 5.3 | 258.696.677 | 590.647.689 |\n| Lưu chuyển tiền thuần từ hoạt động đầu tư | 30 | | (34.825.666.728) | (121.758.529.362) |",
    "questions": [
      {
        "question": "Lưu chuyển tiền thuần từ hoạt động đầu tư kỳ này là bao nhiêu?",
        "difficulty": "Easy_QA"
      },
      {
        "question": "Số tiền chi để mua sắm TSCĐ kỳ trước là bao nhiêu VND?",
        "difficulty": "Easy_QA"
      },
      {
        "question": "So sánh tiền thu từ thanh lý, nhượng bán TSCĐ giữa hai kỳ.",
        "difficulty": "Medium_QA"
      },
      {
        "question": "Lưu chuyển tiền thuần từ hoạt động đầu tư kỳ này so với kỳ trước thay đổi như thế nào?",
        "difficulty": "Medium_QA"
      },
      {
        "question": "Đánh giá mức độ đầu tư của công ty trong kỳ này so với kỳ trước.",
        "difficulty": "Medium_SA"
      },
      {
        "question": "Phân tích tác động của việc giảm mạnh chi tiêu cho TSCĐ đến tăng trưởng dài hạn của công ty.",
        "difficulty": "Hard_SA"
      },
      {
        "question": "Nhận định chiến lược quản lý tài sản dài hạn của công ty dựa trên số liệu này.",
        "difficulty": "Hard_SA"
      }
    ]
  },
  {
    "chunk_id": "21",
    "content": "Công ty: Công ty Cổ phần Khoáng sản và Vật liệu Xây dựng Lâm Đồng và Các Công ty Con\nMã cổ phiếu: Không có thông tin được cung cấp trong báo cáo.\nLoại báo cáo: Báo cáo tài chính hợp nhất đã được soát xét giữa niên độ\nThời gian: Cho kỳ kế toán 06 tháng kết thúc ngày 30 tháng 06 năm 2024 (phát hành ngày 26 tháng 08 năm 2024)\nÝ kiến kiểm toán: Chấp nhận toàn phần (dựa trên báo cáo soát xét)\n\nSection: Báo cáo lưu chuyển tiền tệ hợp nhất (Phần III - Lưu chuyển tiền từ hoạt động tài chính và Tổng)\nLoại nội dung: Bảng\n| CHỈ TIÊU | Mã số | Thuyết minh | Kỳ này | Kỳ trước |\n|---|---|---|---|---|\n| III. LƯU CHUYỂN TIỀN TỪ HOẠT ĐỘNG TÀI CHÍNH | | | | |\n| 1. Tiền thu từ đi vay | 33 | 6.1 | 36.343.801.981 | 60.000.000.000 |\n| 2. Tiền trả nợ gốc vay | 34 | 6.2 | (38.978.988.915) | (27.918.368.315) |\n| 3. Cổ tức, lợi nhuận đã trả cho chủ sở hữu | 36 | 4.18.1 | (30.176.700.000) | (38.176.700.000) |\n| Lưu chuyển tiền thuần từ hoạt động tài chính | 40 | | (32.811.886.934) | (6.095.068.315) |\n| LƯU CHUYỂN TIỀN THUẦN TRONG KỲ | 50 | | (15.534.808.765) | (34.311.154.991) |\n| Tiền và tương đương tiền đầu năm | 60 | | 71.485.359.897 | 91.532.223.138 |\n| Ảnh hưởng của thay đổi tỷ giá hối đoái quy đổi ngoại tệ | 61 | | 34.442.681 | 2.566.881 |\n| TIỀN VÀ TƯƠNG ĐƯƠNG TIỀN CUỐI KỲ | 70 | 4.1 | 55.916.108.451 | 57.218.501.266 |",
    "questions": [
      {
        "question": "Tổng lưu chuyển tiền thuần trong kỳ này là bao nhiêu?",
        "difficulty": "Easy_QA"
      },
      {
        "question": "Tiền và tương đương tiền cuối kỳ này là bao nhiêu VND?",
        "difficulty": "Easy_QA"
      },
      {
        "question": "So sánh tiền thu từ đi vay kỳ này với kỳ trước.",
        "difficulty": "Medium_QA"
      },
      {
        "question": "Lưu chuyển tiền thuần từ hoạt động tài chính thay đổi như thế nào giữa hai kỳ?",
        "difficulty": "Medium_QA"
      },
      {
        "question": "Đánh giá mức độ phụ thuộc của công ty vào nguồn vốn vay trong kỳ này.",
        "difficulty": "Medium_SA"
      },
      {
        "question": "Phân tích tác động của việc giảm cổ tức chi trả đến lợi ích của cổ đông và chiến lược tài chính của công ty.",
        "difficulty": "Hard_SA"
      },
      {
        "question": "Dự báo khả năng duy trì mức tiền và tương đương tiền hiện tại dựa trên lưu chuyển tiền thuần trong kỳ.",
        "difficulty": "Hard_SA"
      }
    ]
  }
]